MANIFEST.in
README.md
requirements.txt
setup.cfg
setup.py
syseleven/__init__.py
syseleven.cloudutilslibs.egg-info/PKG-INFO
syseleven.cloudutilslibs.egg-info/SOURCES.txt
syseleven.cloudutilslibs.egg-info/dependency_links.txt
syseleven.cloudutilslibs.egg-info/namespace_packages.txt
syseleven.cloudutilslibs.egg-info/not-zip-safe
syseleven.cloudutilslibs.egg-info/pbr.json
syseleven.cloudutilslibs.egg-info/requires.txt
syseleven.cloudutilslibs.egg-info/top_level.txt
syseleven/cloudutilslibs/__init__.py
syseleven/cloudutilslibs/kclient.py
syseleven/cloudutilslibs/log.py
syseleven/cloudutilslibs/openstackclients.py
syseleven/cloudutilslibs/utils.py